setup.py
bigreddy/__init__.py
bigreddy.egg-info/PKG-INFO
bigreddy.egg-info/SOURCES.txt
bigreddy.egg-info/dependency_links.txt
bigreddy.egg-info/entry_points.txt
bigreddy.egg-info/requires.txt
bigreddy.egg-info/top_level.txt