Metadata-Version: 1.1
Name: bigreddy
Version: 0.1.0
Summary: BigReddy generates pseudo-philosophical and pseudo-poetic ramblings using a Markov chain.
Home-page: https://nadh.in
Author: Kailash Nadh
Author-email: kailash@nadh.in
License: MIT
Download-URL: https://github.com/rainmattertech/pykiteconnect
Platform: UNKNOWN
Classifier: Topic :: Games/Entertainment
Classifier: Natural Language :: English
Classifier: License :: OSI Approved :: MIT License
Classifier: Programming Language :: Python :: 3.3
Classifier: Programming Language :: Python :: 3.4
Classifier: Programming Language :: Python :: 3.5
Classifier: Topic :: Software Development :: Libraries :: Python Modules
